{"hash":"ce71ff6bc25369234b98dbfc3d1fe1d41d133d5b","data":{"posts":{"totalCount":6,"pageInfo":{"totalPages":3,"currentPage":1,"isFirst":true,"isLast":false},"edges":[{"node":{"id":"3ec855ff43907f929fee400f80cb7f68","title":"bat auto run","description":"开机自动运行bat脚本","date":"December 17, 2020","path":"/block/2020/12/17/bat-auto-run/","tags":[{"id":"黑科技","title":"黑科技","path":"/tag/%E9%BB%91%E7%A7%91%E6%8A%80/"}]}},{"node":{"id":"aa6a23049829a00c40176785521bae7e","title":"tslint","description":"ts lint 问题汇总","date":"January 27, 2020","path":"/block/2020/01/27/tslint/","tags":[{"id":"tslint","title":"tslint","path":"/tag/tslint/"}]}}]},"tags":{"edges":[{"node":{"title":"黑科技","path":"/tag/%E9%BB%91%E7%A7%91%E6%8A%80/"}},{"node":{"title":"mybatis","path":"/tag/mybatis/"}},{"node":{"title":"tslint","path":"/tag/tslint/"}},{"node":{"title":"gridsome","path":"/tag/gridsome/"}},{"node":{"title":"maven","path":"/tag/maven/"}},{"node":{"title":"webpack","path":"/tag/webpack/"}}]}},"context":{}}